{
  "review": [
    {
      "id": "a171",
      "place_id": "222679784",
      "nickname": "아이디",
      "password": "ㅂlalfqjsgh",
      "title": "닉네임",
      "content": "내용",
      "createAt": "2024년 2월 29일 오전 2:53"
    },
    {
      "id": "6fc1",
      "place_id": "19513335",
      "nickname": "123",
      "password": "123",
      "title": "123",
      "content": "123123123",
      "createAt": "2024년 2월 29일 오전 2:59"
    },
    {
      "id": "4586",
      "place_id": "7897582",
      "nickname": "123",
      "password": "123",
      "title": "asdfasdfsadf",
      "content": "asdfasdfwe23123123123",
      "createAt": "2024년 2월 29일 오전 2:59"
    },
    {
      "id": "8281",
      "place_id": "7897582",
      "nickname": "44",
      "password": "44",
      "title": "44",
      "content": "5555",
      "createAt": "2024년 2월 29일 오전 3:01"
    }
  ]
}